{
  "build": "py38_1003",
  "build_number": 1003,
  "channel": "https://conda.anaconda.org/conda-forge/win-64",
  "constrains": [
    "python_abi * *_cp38"
  ],
  "depends": [
    "python >=3.8,<3.9.0a0"
  ],
  "extracted_package_dir": "C:\\Users\\ronie\\Anaconda2\\pkgs\\wincertstore-0.2-py38_1003",
  "features": "",
  "files": [
    "Lib/site-packages/__pycache__/wincertstore.cpython-38.pyc",
    "Lib/site-packages/wincertstore-0.2-py3.8.egg-info",
    "Lib/site-packages/wincertstore.py",
    ".nonadmin"
  ],
  "fn": "wincertstore-0.2-py38_1003.tar.bz2",
  "license": "PSF 2",
  "link": {
    "source": "C:\\Users\\ronie\\Anaconda2\\pkgs\\wincertstore-0.2-py38_1003",
    "type": 1
  },
  "md5": "121788810b4fd722fea7689e5e89e552",
  "name": "wincertstore",
  "package_tarball_full_path": "C:\\Users\\ronie\\Anaconda2\\pkgs\\wincertstore-0.2-py38_1003.tar.bz2",
  "paths_data": {
    "paths": [
      {
        "_path": "Lib/site-packages/__pycache__/wincertstore.cpython-38.pyc",
        "path_type": "hardlink",
        "sha256": "48c63db365efc4f548f27ab9030c3cd9ec14a5012c4cc35150dd13cacbf9a62b",
        "sha256_in_prefix": "48c63db365efc4f548f27ab9030c3cd9ec14a5012c4cc35150dd13cacbf9a62b",
        "size_in_bytes": 11119
      },
      {
        "_path": "Lib/site-packages/wincertstore-0.2-py3.8.egg-info",
        "path_type": "hardlink",
        "sha256": "be59641c20270fd1bd0dd362080d9f1c33586f91971f9cc5630f0b338f119184",
        "sha256_in_prefix": "be59641c20270fd1bd0dd362080d9f1c33586f91971f9cc5630f0b338f119184",
        "size_in_bytes": 5788
      },
      {
        "_path": "Lib/site-packages/wincertstore.py",
        "path_type": "hardlink",
        "sha256": "9eb1879f68dcdd125eb0ed737ed331f16e335a6a5208ec9f26fd3dd6220cfd08",
        "sha256_in_prefix": "9eb1879f68dcdd125eb0ed737ed331f16e335a6a5208ec9f26fd3dd6220cfd08",
        "size_in_bytes": 11873
      }
    ],
    "paths_version": 1
  },
  "requested_spec": "None",
  "sha256": "d90d1b70f5070e98166fdb57d3b42b03b85f444a8463d13c5efa067651fc03a8",
  "size": 13521,
  "subdir": "win-64",
  "timestamp": 1572619823136,
  "track_features": "",
  "url": "https://conda.anaconda.org/conda-forge/win-64/wincertstore-0.2-py38_1003.tar.bz2",
  "version": "0.2"
}